CHANGES.txt
DEPENDENCES.txt
README.txt
setup.py
src/ng/__init__.py
src/ng.site.addon.tag.egg-info/PKG-INFO
src/ng.site.addon.tag.egg-info/SOURCES.txt
src/ng.site.addon.tag.egg-info/dependency_links.txt
src/ng.site.addon.tag.egg-info/namespace_packages.txt
src/ng.site.addon.tag.egg-info/not-zip-safe
src/ng.site.addon.tag.egg-info/requires.txt
src/ng.site.addon.tag.egg-info/top_level.txt
src/ng/site/__init__.py
src/ng/site/addon/__init__.py
src/ng/site/addon/tag/__init__.py
src/ng/site/addon/tag/configure.zcml
src/ng/site/addon/tag/ng.site.addon.tag.txt
src/ng/site/addon/tag/etc/ng.site.addon.tag-configure.zcml
src/ng/site/addon/tag/install/__init__.py
src/ng/site/addon/tag/install/configure.zcml
src/ng/site/addon/tag/install/install_content.py
src/ng/site/addon/tag/install/install_index.py
src/ng/site/addon/tag/install/install_rubricator.py
src/ng/site/addon/tag/wave/__init__.py
src/ng/site/addon/tag/wave/configure.zcml
src/ng/site/addon/tag/wave/interfaces.py